gulp_setup/__data__/uff/rappe.csv
gulp_setup/__data__/uff/uff4mof.csv
gulp_setup/__init__.py
gulp_setup/gulp_setter.py
gulp_setup/mmanalysis.py
gulp_setup-0.1.5.dist-info/METADATA
gulp_setup-0.1.5.dist-info/WHEEL
gulp_setup-0.1.5.dist-info/entry_points.txt
gulp_setup-0.1.5.dist-info/RECORD
