Metadata-Version: 2.1
Name: gulp_setup
Version: 0.1.5
Summary: A python script to convert any ase input file to gulp (.gin)
License: MIT
Author: Dinga Wonanke
Requires-Python: >=3.6,<4.0
Classifier: License :: OSI Approved :: MIT License
Classifier: Programming Language :: Python :: 3
Classifier: Programming Language :: Python :: 3.6
Classifier: Programming Language :: Python :: 3.7
Classifier: Programming Language :: Python :: 3.8
Classifier: Programming Language :: Python :: 3.9
Classifier: Programming Language :: Python :: 3.10
Classifier: Programming Language :: Python :: 3.11
Classifier: Programming Language :: Python :: 3.12
Requires-Dist: mofstructure (>=0.1.8.3,<0.2.0.0)
